Workbook

Sheet Meeting List
A1: Sr No. | B1: Timeslot | C1: Investor (Fund) | D1: Investor Rep | E1: Founder (Company) | F1: Founder Name | G1: Room / Location | H1: Founder Runner | I1: Investor Runner | J1: Meeting Started (yes / no) | K1: Status | L1: Started At | M1: Started By
A2: 1 | B2: 10:00-10:35 | C2: Eight Roads | D2: Diwakar Anand | E2: Clientell | F2: Saahil Dhaka | H2: Apurva
A3: 2 | B3: 10:00-10:35 | C3: Prosus | D3: Soumya Chauhan | E3: Futwork | F3: Niranjan Nakhate | H3: Charu
A4: 3 | B4: 10:00-10:35 | C4: Creaegis | D4: Amit Ranade | E4: Handpickd | F4: Anant V. Goel | H4: Chaitanya
A5: 4 | B5: 10:00-10:35 | C5: ICICI Venture | D5: Shashwat Madan | E5: iDo Devices | F5: Ashita Gupta, Shalabh Srivastava | H5: Charu
A6: 5 | B6: 10:00-10:35 | C6: B Capital | D6: Deepanshu Pattanayak, Akash Khandelwal, Karan Mohla | E6: Lucira | F6: Rupesh Jain | H6: Apurva
A7: 6 | B7: 10:00-10:35 | C7: 360 One | D7: Tanmay Parasramka | E7: Procol | F7: Gaurav Baheti | H7: Sreenidhi
A8: 7 | B8: 10:45-11:20 | C8: Sorin Investments | D8: Sanchita Tibrewal | E8: FOXO | F8: Subhendu Panigrahi | H8: Akshat
A9: 8 | B9: 10:45-11:20 | C9: Creaegis | D9: Amit Ranade | E9: Futwork | F9: Niranjan Nakhate | H9: Charu
A10: 9 | B10: 10:45-11:20 | C10: SMBC Asia Rising Fund | D10: Rajeev Ranka, Mayank Agarwal | E10: iDo Devices | F10: Ashita Gupta, Shalabh Srivastava | H10: Charu
A11: 10 | B11: 10:45-11:20 | C11: Eight Roads | D11: Diwakar Anand | E11: LightFury | F11: Karan Shroff | H11: Apurva
A12: 11 | B12: 10:45-11:20 | C12: Sorin Investments | D12: Alok Anand Patra | E12: Lucira | F12: Rupesh Jain | H12: Apurva
A13: 12 | B13: 10:45-11:20 | C13: Dharana Capital | D13: Parshva Shah | E13: Procol | F13: Gaurav Baheti | H13: Sreenidhi
... A51: 50 | B51: 14:30-14:50 | C51: Creaegis | D51: Amit Ranade | E51: Wiffy | F51: Vikram S. | H51: Akshat

Sheet Invetsor View
B1: Runner | C1: Fund Name | D1: Fund Representative | E1: Room | F1: 2:30–3:00 | G1: 3:00–3:30 | H1: 3:30–4:00 | I1: 4:00–4:30 | J1: 4:30–5:00 | K1: # of Meetings | L1: Mailed on 07022026
B2: Udayan | C2: GIC | D2: Gaurav Jain | E2: FF-Curate | G2: A-IDfy | H2: A-smallcase | I2: B-Optimized Electrotech | K2: =IFERROR(__xludf.DUMMYFUNCTION("COUNTUNIQUE(F2:J2)"),3) -> 3 | L2: Y
B3: Udayan | D3: Anand Khetan
B4: Udayan | C4: IFC | D4: Shalabh Tandon | E4: GF-Navigate | F4: A-TestMu (formerly Lambdatest) | I4: A-iDO Devices | K4: =IFERROR(__xludf.DUMMYFUNCTION("COUNTUNIQUE(F4:J4)"),2) -> 2 | L4: Y - had mailed on 06/02/2026
B5: Udayan | D5: Treasa Mathew
B6: Udayan | D6: R. Hirawat
B7: Udayan | D7: Gordon Chan
B8: Udayan | C8: Oman Investment Authority | D8: Ali Abdulhussain | E8: GF-Clout | F8: A-iDO Devices | G8: A-Cashify | H8: A-Euler Motors | I8: A-IDfy | J8: A-smallcase | K8: =IFERROR(__xludf.DUMMYFUNCTION("COUNTUNIQUE(F8:J8)"),5) -> 5 | L8: Y
B9: Udayan | D9: Mahmoud Al Khatri
B10: Udayan | C10: Neo Secondaries Fund | D10: Nitin Agarwal | E10: FF-Aspire | F10: A-Cashify | G10: A-Spinny | H10: A-iDO Devices | I10: A-smallcase | J10: A-Optimo Loans | K10: =IFERROR(__xludf.DUMMYFUNCTION("COUNTUNIQUE(F10:J10)"),5) -> 5 | L10: Y
B11: Udayan | C11: Pavilion Capital | D11: Khor Boon How | E11: FF-Ponder | F11: A-Optimo Loans | G11: A-Squad | H11: A-TestMu (formerly Lambdatest) | I11: B-Aerem | J11: B-Optimized Electrotech | K11: =IFERROR(__xludf.DUMMYFUNCTION("COUNTUNIQUE(F11:J11)"),5) -> 5 | L11: Y
B12: Udayan | D12: Sam
B13: Udayan | C13: Nippon India | D13: Ankit Agarwal | E13: GF-Library | F13: B-Aerem | G13: B-Virohan | H13: A-Optimo Loans | I13: B-Stage | K13: =IFERROR(__xludf.DUMMYFUNCTION("COUNTUNIQUE(F13:J13)"),4) -> 4 | L13: Y
B14: Apurva | C14: Transsion | D14: George Li | E14: FF-Library | F14: B-Stage | G14: A-Euler Motors | H14: A-Spinny | J14: A-iDO Devices | K14: =IFERROR(__xludf.DUMMYFUNCTION("COUNTUNIQUE(F14:J14)"),4) -> 4 | L14: Y
B15: Apurva | C15: Catamaran | D15: Sheetal Bhat | E15: FF-Balance | K15: =IFERROR(__xludf.DUMMYFUNCTION("COUNTUNIQUE(F15:J15)"),0) -> 0
B16: Apurva | C16: Unilever Ventures | D16: Pawan Chaturvedi | E16: FF-Buzz | F16: B-SuperK | K16: =IFERROR(__xludf.DUMMYFUNCTION("COUNTUNIQUE(F16:J16)"),1) -> 1 | L16: Y
B17: Apurva | D17: Devesh Papney
B18: Apurva | D18: Priyanka Thakkar
B19: Apurva | C19: Transpose Platform | D19: Fiyin Olayisade | E19: GF-Library | F19: A-Squad | K19: =IFERROR(__xludf.DUMMYFUNCTION("COUNTUNIQUE(F19:J19)"),1) -> 1 | L19: Y
B20: Apurva | D20: Shashank P S
B21: Apurva | C21: Evolvence Equity Partners | D21: Anoushka | E21: FF-Introspect | F21: A-IDfy | H21: A-Cashify | K21: =IFERROR(__xludf.DUMMYFUNCTION("COUNTUNIQUE(F21:J21)"),2) -> 2 | L21: Y
B22: Apurva | C22: Mirabilis Investment Trust | D22: Boris DSouza | E22: FF-Balance | H22: A-IDfy | I22: A-Cashify | K22: =IFERROR(__xludf.DUMMYFUNCTION("COUNTUNIQUE(F22:J22)"),2) -> 2 | L22: Y
B23: Apurva | C23: Prosperity 7 | D23: Balsam Alsaif | E23: GF-LAZE | G23: A-TestMu (formerly Lambdatest) | H23: B-Optimized Electrotech | K23: =IFERROR(__xludf.DUMMYFUNCTION("COUNTUNIQUE(F23:J23)"),2) -> 2 | L23: Y
B24: Apurva | D24: Raed Twaily
B25: Apurva | D25: Omar Alnammary
B26: Apurva | D26: Abhishek Shukla
K27: =SUM(K2:K26) -> 36

Sheet Founder View
A1: Runner | B1: Company | C1: Founder Name | D1: 2:30–3:00 | E1: 3:00–3:30 | F1: 3:30–4:00 | G1: 4:00–4:30 | H1: 4:30–5:00 | I1: # of Meetings
A2: Sumangal | B2: A-Cashify | C2: Mandeep | D2: Neo Secondaries Fund | E2: Oman Investment Authority | F2: Evolvence Equity Partners | G2: Mirabilis Investment Trust | I2: =IFERROR(__xludf.DUMMYFUNCTION("COUNTUNIQUE(D2:H2)"),4) -> 4
D3: =IFERROR(VLOOKUP(D2,'Invetsor View'!$C$1:$E$26,3,FALSE()),) -> FF-Aspire | E3: =IFERROR(VLOOKUP(E2,'Invetsor View'!$C$1:$E$26,3,FALSE()),) -> GF-Clout | F3: =IFERROR(VLOOKUP(F2,'Invetsor View'!$C$1:$E$26,3,FALSE()),) -> FF-Introspect | G3: =IFERROR(VLOOKUP(G2,'Invetsor View'!$C$1:$E$26,3,FALSE()),) -> FF-Balance | H3: =IFERROR(VLOOKUP(H2,'Invetsor View'!$C$1:$E$26,3,FALSE()),) -> 0
A4: Sumangal | B4: A-Euler Motors | C4: Sourav | E4: Transsion | F4: Oman Investment Authority | I4: =IFERROR(__xludf.DUMMYFUNCTION("COUNTUNIQUE(D4:H4)"),2) -> 2
D5: =IFERROR(VLOOKUP(D4,'Invetsor View'!$C$1:$E$26,3,FALSE()),) -> 0 | E5: =IFERROR(VLOOKUP(E4,'Invetsor View'!$C$1:$E$26,3,FALSE()),) -> FF-Library | F5: =IFERROR(VLOOKUP(F4,'Invetsor View'!$C$1:$E$26,3,FALSE()),) -> GF-Clout | G5: =IFERROR(VLOOKUP(G4,'Invetsor View'!$C$1:$E$26,3,FALSE()),) -> 0 | H5: =IFERROR(VLOOKUP(H4,'Invetsor View'!$C$1:$E$26,3,FALSE()),) -> 0
A6: Sumangal | B6: A-IDfy | C6: Ashok | D6: Evolvence Equity Partners | E6: GIC | F6: Mirabilis Investment Trust | G6: Oman Investment Authority | I6: =IFERROR(__xludf.DUMMYFUNCTION("COUNTUNIQUE(D6:H6)"),4) -> 4
D7: =IFERROR(VLOOKUP(D6,'Invetsor View'!$C$1:$E$26,3,FALSE()),) -> FF-Introspect | E7: =IFERROR(VLOOKUP(E6,'Invetsor View'!$C$1:$E$26,3,FALSE()),) -> FF-Curate | F7: =IFERROR(VLOOKUP(F6,'Invetsor View'!$C$1:$E$26,3,FALSE()),) -> FF-Balance | G7: =IFERROR(VLOOKUP(G6,'Invetsor View'!$C$1:$E$26,3,FALSE()),) -> GF-Clout | H7: =IFERROR(VLOOKUP(H6,'Invetsor View'!$C$1:$E$26,3,FALSE()),) -> 0
A8: Sumangal | B8: A-Optimo Loans | C8: Prashant | D8: Pavilion Capital | F8: Nippon India | H8: Neo Secondaries Fund | I8: =IFERROR(__xludf.DUMMYFUNCTION("COUNTUNIQUE(D8:H8)"),3) -> 3
D9: =IFERROR(VLOOKUP(D8,'Invetsor View'!$C$1:$E$26,3,FALSE()),) -> FF-Ponder | E9: =IFERROR(VLOOKUP(E8,'Invetsor View'!$C$1:$E$26,3,FALSE()),) -> 0 | F9: =IFERROR(VLOOKUP(F8,'Invetsor View'!$C$1:$E$26,3,FALSE()),) -> GF-Library | G9: =IFERROR(VLOOKUP(G8,'Invetsor View'!$C$1:$E$26,3,FALSE()),) -> 0 | H9: =IFERROR(VLOOKUP(H8,'Invetsor View'!$C$1:$E$26,3,FALSE()),) -> FF-Aspire
A10: Sumangal | B10: A-Spinny | C10: Niraj | E10: Neo Secondaries Fund | F10: Transsion | I10: =IFERROR(__xludf.DUMMYFUNCTION("COUNTUNIQUE(D10:H10)"),2) -> 2
D11: =IFERROR(VLOOKUP(D10,'Invetsor View'!$C$1:$E$26,3,FALSE()),) -> 0 | E11: =IFERROR(VLOOKUP(E10,'Invetsor View'!$C$1:$E$26,3,FALSE()),) -> FF-Aspire | F11: =IFERROR(VLOOKUP(F10,'Invetsor View'!$C$1:$E$26,3,FALSE()),) -> FF-Library | G11: =IFERROR(VLOOKUP(G10,'Invetsor View'!$C$1:$E$26,3,FALSE()),) -> 0 | H11: =IFERROR(VLOOKUP(H10,'Invetsor View'!$C$1:$E$26,3,FALSE()),) -> 0
A12: Sumangal | B12: A-Squad | C12: Apurv | D12: Transpose Platform | E12: Pavilion Capital | I12: =IFERROR(__xludf.DUMMYFUNCTION("COUNTUNIQUE(D12:H12)"),2) -> 2
D13: =IFERROR(VLOOKUP(D12,'Invetsor View'!$C$1:$E$26,3,FALSE()),) -> GF-Library | E13: =IFERROR(VLOOKUP(E12,'Invetsor View'!$C$1:$E$26,3,FALSE()),) -> FF-Ponder | F13: =IFERROR(VLOOKUP(F12,'Invetsor View'!$C$1:$E$26,3,FALSE()),) -> 0 | G13: =IFERROR(VLOOKUP(G12,'Invetsor View'!$C$1:$E$26,3,FALSE()),) -> 0 | H13: =IFERROR(VLOOKUP(H12,'Invetsor View'!$C$1:$E$26,3,FALSE()),) -> 0
A14: Sumangal | B14: A-TestMu (formerly Lambdatest) | C14: Asad | D14: IFC | E14: Prosperity 7 | F14: Pavilion Capital | I14: =IFERROR(__xludf.DUMMYFUNCTION("COUNTUNIQUE(D14:H14)"),3) -> 3
D15: =IFERROR(VLOOKUP(D14,'Invetsor View'!$C$1:$E$26,3,FALSE()),) -> GF-Navigate | E15: =IFERROR(VLOOKUP(E14,'Invetsor View'!$C$1:$E$26,3,FALSE()),) -> GF-LAZE | F15: =IFERROR(VLOOKUP(F14,'Invetsor View'!$C$1:$E$26,3,FALSE()),) -> FF-Ponder | G15: =IFERROR(VLOOKUP(G14,'Invetsor View'!$C$1:$E$26,3,FALSE()),) -> 0 | H15: =IFERROR(VLOOKUP(H14,'Invetsor View'!$C$1:$E$26,3,FALSE()),) -> 0
A16: Yash | B16: A-iDO Devices | C16: Ashita | D16: Oman Investment Authority | E16: UTEC | F16: Neo Secondaries Fund | G16: IFC | H16: Transsion | I16: =IFERROR(__xludf.DUMMYFUNCTION("COUNTUNIQUE(D16:H16)"),5) -> 5
D17: =IFERROR(VLOOKUP(D16,'Invetsor View'!$C$1:$E$26,3,FALSE()),) -> GF-Clout | E17: =IFERROR(VLOOKUP(E16,'Invetsor View'!$C$1:$E$26,3,FALSE()),) -> 0 | F17: =IFERROR(VLOOKUP(F16,'Invetsor View'!$C$1:$E$26,3,FALSE()),) -> FF-Aspire | G17: =IFERROR(VLOOKUP(G16,'Invetsor View'!$C$1:$E$26,3,FALSE()),) -> GF-Navigate | H17: =IFERROR(VLOOKUP(H16,'Invetsor View'!$C$1:$E$26,3,FALSE()),) -> FF-Library
A18: Yash | B18: A-smallcase | C18: Vasanth | F18: GIC | G18: Neo Secondaries Fund | H18: Oman Investment Authority | I18: =IFERROR(__xludf.DUMMYFUNCTION("COUNTUNIQUE(D18:H18)"),3) -> 3
D19: =IFERROR(VLOOKUP(D18,'Invetsor View'!$C$1:$E$26,3,FALSE()),) -> 0 | E19: =IFERROR(VLOOKUP(E18,'Invetsor View'!$C$1:$E$26,3,FALSE()),) -> 0 | F19: =IFERROR(VLOOKUP(F18,'Invetsor View'!$C$1:$E$26,3,FALSE()),) -> FF-Curate | G19: =IFERROR(VLOOKUP(G18,'Invetsor View'!$C$1:$E$26,3,FALSE()),) -> FF-Aspire | H19: =IFERROR(VLOOKUP(H18,'Invetsor View'!$C$1:$E$26,3,FALSE()),) -> GF-Clout
A20: Yash | B20: B-Aerem | C20: Anand | D20: Nippon India | G20: Pavilion Capital | I20: =IFERROR(__xludf.DUMMYFUNCTION("COUNTUNIQUE(D20:H20)"),2) -> 2
D21: =IFERROR(VLOOKUP(D20,'Invetsor View'!$C$1:$E$26,3,FALSE()),) -> GF-Library | E21: =IFERROR(VLOOKUP(E20,'Invetsor View'!$C$1:$E$26,3,FALSE()),) -> 0 | F21: =IFERROR(VLOOKUP(F20,'Invetsor View'!$C$1:$E$26,3,FALSE()),) -> 0 | G21: =IFERROR(VLOOKUP(G20,'Invetsor View'!$C$1:$E$26,3,FALSE()),) -> FF-Ponder | H21: =IFERROR(VLOOKUP(H20,'Invetsor View'!$C$1:$E$26,3,FALSE()),) -> 0
A22: Yash | B22: B-Optimized Electrotech | C22: Sandeep | F22: Prosperity 7 | G22: GIC | H22: Pavilion Capital | I22: =IFERROR(__xludf.DUMMYFUNCTION("COUNTUNIQUE(D22:H22)"),3) -> 3
D23: =IFERROR(VLOOKUP(D22,'Invetsor View'!$C$1:$E$26,3,FALSE()),) -> 0 | E23: =IFERROR(VLOOKUP(E22,'Invetsor View'!$C$1:$E$26,3,FALSE()),) -> 0 | F23: =IFERROR(VLOOKUP(F22,'Invetsor View'!$C$1:$E$26,3,FALSE()),) -> GF-LAZE | G23: =IFERROR(VLOOKUP(G22,'Invetsor View'!$C$1:$E$26,3,FALSE()),) -> FF-Curate | H23: =IFERROR(VLOOKUP(H22,'Invetsor View'!$C$1:$E$26,3,FALSE()),) -> FF-Ponder
A24: Yash | B24: B-Stage | C24: Vinay | D24: Transsion | G24: Nippon India | I24: =IFERROR(__xludf.DUMMYFUNCTION("COUNTUNIQUE(D24:H24)"),2) -> 2
D25: =IFERROR(VLOOKUP(D24,'Invetsor View'!$C$1:$E$26,3,FALSE()),) -> FF-Library | E25: =IFERROR(VLOOKUP(E24,'Invetsor View'!$C$1:$E$26,3,FALSE()),) -> 0 | F25: =IFERROR(VLOOKUP(F24,'Invetsor View'!$C$1:$E$26,3,FALSE()),) -> 0 | G25: =IFERROR(VLOOKUP(G24,'Invetsor View'!$C$1:$E$26,3,FALSE()),) -> GF-Library | H25: =IFERROR(VLOOKUP(H24,'Invetsor View'!$C$1:$E$26,3,FALSE()),) -> 0
A26: Yash | B26: B-SuperK | C26: Neeraj | D26: Unilever Ventures | I26: =IFERROR(__xludf.DUMMYFUNCTION("COUNTUNIQUE(D26:H26)"),1) -> 1
D27: =IFERROR(VLOOKUP(D26,'Invetsor View'!$C$1:$E$26,3,FALSE()),) -> FF-Buzz | E27: =IFERROR(VLOOKUP(E26,'Invetsor View'!$C$1:$E$26,3,FALSE()),) -> 0 | F27: =IFERROR(VLOOKUP(F26,'Invetsor View'!$C$1:$E$26,3,FALSE()),) -> 0 | G27: =IFERROR(VLOOKUP(G26,'Invetsor View'!$C$1:$E$26,3,FALSE()),) -> 0 | H27: =IFERROR(VLOOKUP(H26,'Invetsor View'!$C$1:$E$26,3,FALSE()),) -> 0
A28: Yash | B28: B-Virohan | C28: Kunaal | E28: Nippon India | I28: =IFERROR(__xludf.DUMMYFUNCTION("COUNTUNIQUE(D28:H28)"),1) -> 1
D29: =IFERROR(VLOOKUP(D28,'Invetsor View'!$C$1:$E$26,3,FALSE()),) -> 0 | E29: =IFERROR(VLOOKUP(E28,'Invetsor View'!$C$1:$E$26,3,FALSE()),) -> GF-Library | F29: =IFERROR(VLOOKUP(F28,'Invetsor View'!$C$1:$E$26,3,FALSE()),) -> 0 | G29: =IFERROR(VLOOKUP(G28,'Invetsor View'!$C$1:$E$26,3,FALSE()),) -> 0 | H29: =IFERROR(VLOOKUP(H28,'Invetsor View'!$C$1:$E$26,3,FALSE()),) -> 0

Sheet Work
B5: Sumangal | C5: Founder Runner | I5: Room Name | J5: Floor | K5: Capacity
B6: Yash | C6: Founder Runner | I6: Laze room | J6: Ground Floor | K6: 6
B7: Joseph | C7: Founder Runner Backup | I7: Clout | J7: Ground Floor | K7: 3
I8: Navigate | J8: Ground Floor | K8: 10
B9: Udayan | C9: Investor Runner | I9: Buzz | J9: First Floor | K9: 10
B10: Apurva | C10: Investor Runner | I10: Ponder | J10: First Floor | K10: 4
B11: Ankush | C11: Investor Runner Backup | I11: Balance | J11: First Floor | K11: 2
I12: Aspire | J12: First Floor | K12: 3
B13: Sreeneedhi | C13: Registration | I13: Curate | J13: First Floor | K13: 4
I14: Introspect | J14: First Floor | K14: 3
I15: Library (FF) | J15: First Floor | K15: 6
I16: Library (GF) | J16: Ground Floor | K16: 14
B18: Get Laptops/ iPads
B19: Sheet will be shared with you
B20: Backup folks act as a releiver for the runner as well as help in finding a person if required
B21: Contact details for founder runners let me know if you have all/ which are missing
B22: For investors we will ask Alok
I24: Change Log
B25: Sreeneedhi - on spot scheduling | I25: Catamaran Dropped
I26: iDO given to UTEC at 3PM

Sheet Attendance Sheet
B1: Company Name | C1: Company with Classification | D1: Attending LP BluSwan
B2: Cashify | C2: A-Cashify | D2: Y
B3: Euler | C3: A-Euler Motors | D3: Y
B4: Idfy | C4: A-IDfy | D4: Y
B5: iDO Devices | C5: A-iDO Devices | D5: Y
B6: Optimo Loans | C6: A-Optimo Loans | D6: Y
B7: smallcase | C7: A-smallcase | D7: Y
B8: Squadstack.ai | C8: A-Squad | D8: Y
B9: Spinny | C9: A-Spinny | D9: Y
B10: TestMu (Lambdatest) | C10: A-TestMu (formerly Lambdatest) | D10: Y
B11: Aerem | C11: B-Aerem | D11: Y
B12: Optimized Electrotech | C12: B-Optimized Electrotech | D12: Y
... B16: Confido | C16: A-Confido | D16: Y

Sheet Investor Preferences
A1: Investor Name | B1: Fund Name | C1: Atomicwork | D1: Cashify | E1: Ethereal Machines | F1: Euler Motors | G1: IDfy | H1: iDO Devices | I1: Optimo Loans | J1: smallcase | K1: slice | L1: Squad | M1: Spinny | N1: TestMu (formerly Lambdatest) | O1: Aerem | P1: BatterySmart | Q1: DPDZero | R1: IntrCity | S1: LeverageEdu | T1: Namma Yatri (Moving Tech) | U1: Optimized Electrotech | V1: Pixxel | W1: Servify | X1: Stage | Y1: SuperK | Z1: Ultrahuman | AA1: Virohan
A2: Kiran Mysore | B2: UTEC | H2: Top 3 request | T2: Top 3 Request
A3: ankit agarwal | B3: ankit.agarwal@nipponindiaim.com | C3: Not interested | D3: Not interested | E3: Next Priority | F3: Not interested | G3: Not interested | H3: Interested, can meet later | I3: Next Priority | J3: Interested, can meet later | K3: Not interested | L3: Interested, can meet later | M3: Not interested | N3: Not interested | O3: Top 3 Request | P3: Not interested | Q3: Top 3 Request | R3: Not interested | S3: Not interested | T3: Interested, can meet later | U3: Not interested | V3: Not interested | W3: Not interested | X3: Next Priority | Y3: Interested, can meet later | Z3: Not interested | AA3: Top 3 Request
A4: Gaurav Jain | B4: GIC | C4: Top 3 request | G4: Next Priority | J4: Next Priority | K4: Top 3 request | L4: Top 3 request | U4: Next Priority
A5: Fiyin Olayisade | B5: Transpose Platform | C5: Top 3 request | L5: Top 3 request
A6: George Li | B6: Transsion | C6: Next Priority | D6: Interested, can meet later | F6: Next Priority | H6: Top 3 request | L6: Top 3 request | M6: Next Priority | P6: Interested, can meet later | S6: Interested, can meet later | T6: Interested, can meet later | X6: Next Priority | Y6: Interested, can meet later | Z6: Top 3 Request
A7: Nitin Agarwal | B7: Neo Secondaries Fund | C7: Next Priority | D7: Top 3 request | E7: Interested, can meet later | F7: Interested, can meet later | G7: Not interested | H7: Next Priority | I7: Next Priority | J7: Next Priority | K7: Top 3 request | L7: Interested, can meet later | M7: Top 3 request | N7: Interested, can meet later | O7: Interested, can meet later | P7: Top 3 Request | Q7: Next Priority | R7: Top 3 Request | S7: Interested, can meet later | T7: Next Priority | U7: Interested, can meet later | V7: Interested, can meet later | W7: Interested, can meet later | X7: Interested, can meet later | Z7: Top 3 Request | AA7: Interested, can meet later
A8: Sheetal | B8: Catamaran | C8: Interested, can meet later | E8: Top 3 request | H8: Top 3 request | L8: Interested, can meet later | Q8: Top 3 Request | U8: Top 3 Request | AA8: Interested, can meet later
A9: Boris DSouza | B9: Mirabilis Investment Trust | C9: Not interested | D9: Top 3 request | E9: Not interested | F9: Interested, can meet later | G9: Top 3 request | H9: Next Priority | I9: Not interested | K9: Next Priority | L9: Next Priority | M9: Top 3 request | N9: Interested, can meet later | O9: Interested, can meet later | P9: Not interested | Q9: Top 3 Request | R9: Not interested | T9: Top 3 Request | U9: Not interested | V9: Not interested | W9: Next Priority | X9: Not interested | Y9: Not interested | Z9: Top 3 Request | AA9: Not interested
A10: Ali Abdulhussain | B10: Oman Investment Authority | C10: Not interested | D10: Next Priority | E10: Next Priority | F10: Next Priority | G10: Next Priority | H10: Top 3 request | I10: Not interested | J10: Next Priority | K10: Interested, can meet later | L10: Next Priority | M10: Not interested | N10: Next Priority | O10: Next Priority | P10: Top 3 Request, Next Priority | Q10: Next Priority | R10: Not interested | S10: Not interested | T10: Not interested | U10: Next Priority | V10: Top 3 Request, Next Priority | W10: Not interested | X10: Not interested | Y10: Interested, can meet later | Z10: Next Priority | AA10: Not interested
A11: Khor Boon How | B11: Pavilion Capital | C11: Top 3 request | E11: Interested, can meet later | H11: Interested, can meet later | I11: Next Priority | K11: Top 3 request | L11: Top 3 request | N11: Next Priority | O11: Next Priority | P11: Top 3 Request | Q11: Next Priority | T11: Interested, can meet later | U11: Next Priority | V11: Top 3 Request | X11: Interested, can meet later | Z11: Top 3 Request
A12: Anoushka Bhatia | B12: Evolvence Equity Partners | C12: Next Priority | D12: Top 3 request | E12: Top 3 request | G12: Top 3 request | P12: Top 3 Request | Z12: Top 3 Request
A13: Devesh Papney | B13: Unilever Ventures | Q13: Top 3 Request | Y13: Top 3 Request | Z13: Top 3 Request
A14: Shun Ishikawa | B14: On&Board | C14: Next Priority | E14: Next Priority | G14: Top 3 request | H14: Next Priority | I14: Next Priority | J14: Next Priority | P14: Next Priority | Q14: Next Priority | S14: Next Priority | U14: Top 3 Request | V14: Top 3 Request | Z14: Next Priority
A15: Rahul Hirawat | B15: IFC | C15: Top 3 request | H15: Top 3 request | L15: Top 3 request | N15: Top 3 request
A16: Omar Alnammary | B16: Prosperity 7 | C16: Top 3 request | E16: Next Priority | F16: Interested, can meet later | H16: Interested, can meet later | L16: Interested, can meet later | N16: Top 3 request | P16: Next Priority | U16: Next Priority | V16: Top 3 request

Sheet Summary
A1: Fund Name | B1: Scheduled Meetings | C1: Top 3 Request (No Meeting) | D1: Next Priority (No Meeting) | E1: Interested, Can Meet Later (No Meeting)
A2: GIC | B2: IDfy, smallcase, Optimized Electrotech | C2: Atomicwork, slice, SquadStack | D2: - | E2: -
A3: IFC | B3: TestMu (formerly Lambdatest), iDO Devices | C3: Atomicwork, SquadStack | D3: - | E3: -
A4: Oman Investment Authority | B4: iDO Devices, Cashify, Euler Motors, IDfy, smallcase | C4: BatterySmart, Pixxel | D4: Ethereal Machines, SquadStack, TestMu (formerly Lambdatest), Aerem, DPDZero, Optimized Electrotech, Ultrahuman | E4: slice, SuperK
A5: Neo Fund | B5: Cashify, Spinny, iDO Devices, smallcase, Optimo Loans | C5: slice, BatterySmart, IntrCity, Ultrahuman | D5: Atomicwork, DPDZero, Namma Yatri (Moving Tech) | E5: Ethereal Machines, Euler Motors, SquadStack, TestMu (formerly Lambdatest), Aerem, LeverageEdu, Optimized Electrotech, Pixxel, Servify, Stage, Virohan
A6: Pavilion Capital | B6: Optimo Loans, SquadStack, TestMu (formerly Lambdatest), Aerem, Optimized Electrotech | C6: Atomicwork, slice, BatterySmart, Pixxel, Ultrahuman | D6: DPDZero | E6: Ethereal Machines, iDO Devices, Namma Yatri (Moving Tech), Stage
A7: Nippon India | B7: Aerem, Virohan, Optimo Loans, Stage | C7: DPDZero | D7: Ethereal Machines | E7: iDO Devices, smallcase, SquadStack, Namma Yatri (Moving Tech), SuperK
A8: Transsion | B8: Stage, Euler Motors, Spinny, iDO Devices | C8: SquadStack, Ultrahuman | D8: Atomicwork | E8: Cashify, BatterySmart, LeverageEdu, Namma Yatri (Moving Tech), SuperK
A9: Catamaran | B9: Optimized Electrotech, iDO Devices | C9: Ethereal Machines, DPDZero | D9: - | E9: Atomicwork, SquadStack, Virohan
A10: Unilever Ventures | B10: SuperK | C10: DPDZero, Ultrahuman | D10: - | E10: -
A11: Transpose Platform | B11: SquadStack | C11: Atomicwork | D11: - | E11: -
A12: Evolvence Equity Partners | B12: IDfy, Cashify | C12: Ethereal Machines, BatterySmart, Ultrahuman | D12: Atomicwork | E12: -
... A14: Prosperity 7 | B14: TestMu (formerly Lambdatest), Optimized Electrotech | C14: Atomicwork, Pixxel | D14: Ethereal Machines, BatterySmart | E14: Euler Motors, iDO Devices, SquadStack

Sheet Long List
A1: Fund Name | B1: Company Name | C1: Status | D1: Email Intro Done
A2: GIC | B2: IDfy | C2: Meeting Scheduled | H2: COUNTA of Company Name | I2: Status
A3: GIC | B3: smallcase | C3: Meeting Scheduled | H3: Fund Name | I3: Interested, Can Meet Later (No Meeting) | J3: Meeting Scheduled | K3: Next Priority (No Meeting) | L3: Top 3 Request (No Meeting) | M3: Grand Total
A4: GIC | B4: Optimized Electrotech | C4: Meeting Scheduled | H4: Catamaran | I4: 3 | J4: 2 | L4: 2 | M4: 7
A5: GIC | B5: Atomicwork | C5: Top 3 Request (No Meeting) | H5: Evolvence Equity Partners | J5: 2 | K5: 1 | L5: 3 | M5: 6
A6: GIC | B6: slice | C6: Top 3 Request (No Meeting) | D6: Sent | H6: GIC | J6: 3 | L6: 3 | M6: 6
A7: GIC | B7: SquadStack | C7: Top 3 Request (No Meeting) | D7: Sent | H7: IFC | J7: 2 | L7: 2 | M7: 4
A8: IFC | B8: TestMu (formerly Lambdatest) | C8: Meeting Scheduled | H8: Mirabilis Investment Trust | I8: 3 | J8: 2 | K8: 4 | L8: 4 | M8: 13
A9: IFC | B9: iDO Devices | C9: Meeting Scheduled | H9: Neo Fund | I9: 11 | J9: 5 | K9: 3 | L9: 4 | M9: 23
A10: IFC | B10: Atomicwork | C10: Top 3 Request (No Meeting) | H10: Nippon India | I10: 5 | J10: 4 | K10: 1 | L10: 1 | M10: 11
A11: IFC | B11: SquadStack | C11: Top 3 Request (No Meeting) | H11: Oman Investment Authority | I11: 2 | J11: 5 | K11: 7 | L11: 2 | M11: 16
A12: Oman Investment Authority | B12: iDO Devices | C12: Meeting Scheduled | H12: Pavilion Capital | I12: 4 | J12: 5 | K12: 1 | L12: 5 | M12: 15
A13: Oman Investment Authority | B13: Cashify | C13: Meeting Scheduled | H13: Prosperity 7 | I13: 3 | J13: 2 | K13: 2 | L13: 2 | M13: 9
A14: Oman Investment Authority | B14: Euler Motors | C14: Meeting Scheduled | H14: Transpose Platform | J14: 1 | L14: 1 | M14: 2
A15: Oman Investment Authority | B15: IDfy | C15: Meeting Scheduled | H15: Transsion | I15: 5 | J15: 4 | K15: 1 | L15: 2 | M15: 12
A16: Oman Investment Authority | B16: smallcase | C16: Meeting Scheduled | H16: Unilever Ventures | J16: 1 | L16: 2 | M16: 3
A17: Oman Investment Authority | B17: BatterySmart | C17: Top 3 Request (No Meeting) | D17: Sent | H17: Grand Total | I17: 36 | J17: 38 | K17: 20 | L17: 33 | M17: 127
A18: Oman Investment Authority | B18: Pixxel | C18: Top 3 Request (No Meeting) | D18: Sent
A19: Oman Investment Authority | B19: Ethereal Machines | C19: Next Priority (No Meeting)
A20: Oman Investment Authority | B20: SquadStack | C20: Next Priority (No Meeting)
A21: Oman Investment Authority | B21: TestMu (formerly Lambdatest) | C21: Next Priority (No Meeting)
A22: Oman Investment Authority | B22: Aerem | C22: Next Priority (No Meeting)
A23: Oman Investment Authority | B23: DPDZero | C23: Next Priority (No Meeting)
A24: Oman Investment Authority | B24: Optimized Electrotech | C24: Next Priority (No Meeting)
A25: Oman Investment Authority | B25: Ultrahuman | C25: Next Priority (No Meeting)
A26: Oman Investment Authority | B26: slice | C26: Interested, Can Meet Later (No Meeting)
A27: Oman Investment Authority | B27: SuperK | C27: Interested, Can Meet Later (No Meeting)
A28: Neo Fund | B28: Cashify | C28: Meeting Scheduled
A29: Neo Fund | B29: Spinny | C29: Meeting Scheduled
A30: Neo Fund | B30: iDO Devices | C30: Meeting Scheduled
... A122: Prosperity 7 | B122: Atomicwork | C122: Top 3 Request (No Meeting)
A123: Prosperity 7 | B123: Pixxel | C123: Top 3 Request (No Meeting) | D123: Sent
A124: Prosperity 7 | B124: Ethereal Machines | C124: Next Priority (No Meeting)
A125: Prosperity 7 | B125: BatterySmart | C125: Next Priority (No Meeting)
A126: Prosperity 7 | B126: Euler Motors | C126: Interested, Can Meet Later (No Meeting)
A127: Prosperity 7 | B127: iDO Devices | C127: Interested, Can Meet Later (No Meeting)
A128: Prosperity 7 | B128: SquadStack | C128: Interested, Can Meet Later (No Meeting)
